{"msX/sGnZQoAcPwXdBTNH7w==":"tickets2-1280x1280.jpeg","w06u14cebYtm5ia4JfOgiQ==":"tickets3-1280x719.jpg","lXh7LuaA64k/yjT569vzyw==":"tickets2-734x734.jpg","3y37hu4K0mua1IlytT9O2Q==":"viber-image-2021-04-27-13-46-52-121x41.png","dAREPcRyhTQn/p/KBXryTQ==":"mbr-1920x1280.jpg","I0Uth5gWUwbQqNHCYier4g==":"mbr-1-1920x1280.jpg","Bi1Lcm5mmDArvgnE8k2uJA==":"mbr-940x626.jpg","DZE4vI0pgOe8VzCeXl+JbQ==":"mbr-940x627.jpg","X88ZIXZkXeEk00yOvPWVnQ==":"mbr-657x438.jpg","V/2iNELGv5g6cEF1pGG8AA==":"mbr-1-657x438.jpg","fLRVBgRUODKiHVBNIxX5Uw==":"tickets2-657x526.jpg","cKn0+Q4rdNstelRL8x1NgQ==":"tickets2-657x526.jpeg","Q99koW+GdJ3VCKDZuTBnNA==":"tickets2-1-657x526.jpeg","AUPLcHa0mB5ztKdZwGc6LQ==":"tickets2-2-657x526.jpeg","dzvZGg2D/SB5mCh/WEjOUA==":"04-657x438.jpg","NdkwjRb2zMgvjosh9vc14Q==":"mbr-2-657x438.jpg","DSqkmEBS87/TATjpzumNTA==":"mbr-3-657x438.jpg","U/rak7r5iQX1b3lngLLBrw==":"02-657x623.jpg","WiiPzIaQXrdIX4Zz3/IyJw==":"02-657x623.jpeg","rleMpIe4IrRYYIBK7IZV9A==":"03-657x438.jpg"}